{
  "solution": {
    "ember-changeset-validations": {
      "impact": "patch",
      "oldVersion": "5.0.0",
      "newVersion": "5.0.1",
      "tagName": "latest",
      "constraints": [
        {
          "impact": "patch",
          "reason": "Appears in changelog section :house: Internal"
        }
      ],
      "pkgJSONPath": "./package.json"
    }
  },
  "description": "## Release (2025-05-01)\n\n* ember-changeset-validations 5.0.1 (patch)\n\n#### :house: Internal\n* `ember-changeset-validations`\n  * [#382](https://github.com/adopted-ember-addons/ember-changeset-validations/pull/382) format changelog with prettier ([@SergeAstapov](https://github.com/SergeAstapov))\n\n#### Committers: 1\n- Sergey Astapov ([@SergeAstapov](https://github.com/SergeAstapov))\n"
}
